{
    "tags": [
        {
            "name": "Famille"
        },
        {
            "name": "Art"
        },
        {
            "name": "Architecture"
        },
        {
            "name": "Nature"
        },
        {
            "name": "Gastronomique"
        },
        {
            "name": "Musée"
        },
        {
            "name": "Panorama"
        },
        {
            "name": "Historique"
        }
    ],
    "sentiers": [
        {
            "titre": "Art en ville de Lausanne",
            "description": "Lausanne regorge d’œuvres d’art inconnues bien qu’à la vue de tous. Revisitez la ville sous un nouveau jour et profitez de vues majestueuses.",
            "duree": "01:40:00",
            "difficulte": "Facile",
            "accessibilite": true,
            "info_transport": "Le départ est à la gare de Lausanne et le trajet se finit à l’arrêt du métro d’Ouchy.",
            "depart": {
                "coordonnees": [46.517264, 6.629346]
            },
            "arrivee": {
                "coordonnees": [46.506953, 6.626603]
            },
            "image": {
                "source": "",
                "url": "https://upload.wikimedia.org/wikipedia/commons/4/42/Plateforme_10.jpg"
            },
            "restauration": "plusieurs restaurants ou cafés sur le parcours",
            "parking": {
                "coordonnees": [46.517264, 6.629346]
            },
            "points_interet": [
                {
                    "nom": "Plateforme 10",
                    "description": "C’est le nouveau quartier des arts de Lausanne. Il est composé de plusieurs musées ainsi que de galeries extérieures. Il s'agit d'une fondation de droit public soutenue par l’Etat de Vaud.",
                    "tags": ["Musée", "Art"],
                    "coordonnees": [46.518273, 6.625511],
                    "open_season": "Toutes",
                    "url": "https://plateforme10.ch",
                    "images": [
                        {
                            "source": "MHM55, CC BY-SA 4.0, via Wikimedia Commons",
                            "url": "https://upload.wikimedia.org/wikipedia/commons/5/51/Plateforme_10%2C_esplanade-01.jpg"
                        },
                        {
                            "source": "Christophe95, CC BY-SA 4.0, via Wikimedia Commons",
                            "url": "https://upload.wikimedia.org/wikipedia/commons/4/42/Plateforme_10.jpg"
                        }
                    ]
                },
                {
                    "nom": "Parc de Milan",
                    "description": "Faites une pause, parcourez le jardin botanique et profitez d’une vue renversante en haut de la colline de Montriond.",
                    "tags": ["Panorama", "Nature"],
                    "coordonnees": [46.515143, 6.624853],
                    "open_season": "Primtemps, Automne",
                    "url": "-",
                    "images": [
                        {
                            "source": "",
                            "url": "https://upload.wikimedia.org/wikipedia/commons/9/90/Jardin_Botanique_25.09.11.JPG"
                        }
                    ]
                },
                {
                    "nom": "Parc du musée olymique",
                    "description": "Plusieurs statues sur le thème des jeux olympiques ou du sport. Laissez-vous surprendre en le parcourant. Une fontaine et des activités pour les enfants sont disponibles également.",
                    "tags": ["Art", "Famille"],
                    "coordonnees": [46.507901, 6.634382],
                    "open_season": "Toutes",
                    "url": "http://lausanne.over-blog.org/pages/Le_jardin_dOlympie-1560965.html",
                    "images": [
                        {
                            "source": "By Lausanne, ville verte",
                            "url": "https://idata.over-blog.com/2/21/56/99/Mus-e-olympique/MO_cuirasse_article_1.jpg"
                        }
                    ]
                },
                {
                    "nom": "Général Guisan",
                    "description": "Le Général Henri Guisan fut le commandant en chef de l'armée suisse pendant la Seconde Guerre mondiale. Connu pour son leadership, il a renforcé la stratégie de défense nationale, notamment avec le Plan Wahlen et le Réduit national, préparant la Suisse à résister à une éventuelle invasion.",
                    "tags": ["Art", "Historique"],
                    "coordonnees": [46.507202, 6.62965],
                    "open_season": "Automne",
                    "url": "-",
                    "images": [
                        {
                            "source": "Patrick Nouhailler's…, CC BY-SA 3.0, via Wikimedia Commons",
                            "url": "https://upload.wikimedia.org/wikipedia/commons/3/3b/Lausanne_-_Lake_Side_-_Vaud%2C_Switzerland_-_panoramio_%2844%29.jpg"
                        }
                    ]
                },
                {
                    "nom": "Nicolas Delémont - Femme à l’enfant",
                    "description": "Cette sculpture qui tend vers l’abstrait nous invite dans l’intimité qu’une femme peut avoir avec son enfant.",
                    "tags": ["Art"],
                    "coordonnees": [46.505255, 6.627512],
                    "open_season": "Toutes",
                    "url": "-",
                    "images": [
                        {
                            "source": "",
                            "url": ""
                        }
                    ]
                },
                {
                    "nom": "Vladimir Tchepelik – Serge Lifar",
                    "description": "Serge Lifar est un grand danseur et chorégraphe qui a terminé sa vie à Lausanne. Vladimir Tchepelik a voulu lui rendre hommage en représentant un moment phare de sa carrière.",
                    "tags": ["Art"],
                    "coordonnees": [46.50553, 6.627067],
                    "open_season": "Hiver",
                    "url": "-",
                    "images": [
                        {
                            "source": "",
                            "url": "https://upload.wikimedia.org/wikipedia/commons/3/35/Serge_Lifar_bij_repetitie_van_Nederlands_Ballet%2C_Bestanddeelnr_912-2421.jpg"
                        }
                    ]
                },
                {
                    "nom": "Angel Durate – Ouverture au monde",
                    "description": "Cet artiste s’inspire de la géométrie dans ses œuvres. Cette sculpture incite ses spectateurs à voyager et s’illumine aux rayons du soleil.",
                    "tags": ["Art"],
                    "coordonnees": [46.504836, 6.625691],
                    "open_season": "Automne, Hiver",
                    "url": "-",
                    "images": [
                        {
                            "source": "AlterVista, CC BY-SA 3.0, via Wikimedia Commons",
                            "url": "https://upload.wikimedia.org/wikipedia/commons/c/c4/Lausanne_Ouchy_Skulptur_besser.JPG"
                        }
                    ]
                },
                {
                    "nom": "Clelia Bettua - Eole",
                    "description": "Cette sculpture indique le sens du vent. Pour le découvrir, trouver le monolithe qui complète le demi-cercle de la girouette.",
                    "tags": ["Art"],
                    "coordonnees": [46.505253, 6.625671],
                    "open_season": "Toutes",
                    "url": "-",
                    "images": [
                        {
                            "source": "Gzzz, CC BY-SA 4.0, via Wikimedia Commons",
                            "url": "https://upload.wikimedia.org/wikipedia/commons/6/69/%C3%89ole_%28Clelia_Bettua%29.jpg"
                        }
                    ]
                }
            ]
        },
        {
            "titre": "L'Histoire d'Yverdon-les-Bains",
            "description": "Connaissez-vous l'histoire de la ville d'Yverdon ? Apprenez-en plus à travers notre chemin",
            "duree": "00:30:00",
            "difficulte": "Facile",
            "accessibilite": true,
            "info_transport": "Ce parcours est une boucle depuis l'arrêt du bus Yverdon, Théâtre Benno Besson des bus 604 et 605.",
            "depart": {
                "coordonnees": [46.77911, 6.642196]
            },
            "arrivee": {
                "coordonnees": [46.77911, 6.642196]
            },
            "image": {
                "source": "Roland Zumbühl (Picswiss), Arlesheim (Commons:Picswiss project), CC BY-SA 3.0, via Wikimedia Commons",
                "url": "https://upload.wikimedia.org/wikipedia/commons/2/25/Picswiss_VD-47-14.jpg"
            },
            "restauration": "plusieurs restaurants ou cafés sur le parcours",
            "parking": {
                "coordonnees": [46.78074, 6.63875]
            },
            "points_interet": [
                {
                    "nom": "Théâtre Benno Besson (1898)",
                    "description": "Le bâtiment a été un casino pendant un siècle. Il a ensuite été transformé en une salle de spectacle et baptisé en hommage à Benno Besson(1922-2006), un homme du Nord vaudois bien connu du monde du théâtre comme acteur et metteur en scène.",
                    "tags": ["Architecture", "Historique"],
                    "coordonnees": [46.779657, 6.64246],
                    "open_season": "Toutes",
                    "url": "https://www.theatrebennobesson.ch/",
                    "images": [
                        {
                            "source": "Sébastien Lassueur, CC BY-SA 4.0, via Wikimedia Commons",
                            "url": "https://upload.wikimedia.org/wikipedia/commons/3/36/Th%C3%A9%C3%A2tre_Benno_Besson%2C_Yverdon-les-Bains.jpg"
                        },
                        {
                            "source": "Erling Mandelmann / photo©ErlingMandelmann.ch",
                            "url": "https://upload.wikimedia.org/wikipedia/commons/a/a6/Benno_Besson_%281983%29_by_Erling_Mandelmann.jpg"
                        }
                    ]
                },
                {
                    "nom": "Temple national (1757)",
                    "description": "La chapelle urbaine Notre-Dame, mentionnée pour la première fois en 1379, a subi des modifications majeures en 1508-1509, notamment la construction d'une chapelle attenante dédiée aux saints Roch et Sébastien. En 1536, la conquête bernoise a entraîné la démolition du chœur et la réorganisation de l'église en temple protestant. Aujourd'hui, il reste principalement le clocher médiéval du XIVe siècle, rehaussé entre 1608 et 1609, avec un ensemble de cloches médiévales unique en Europe.",
                    "tags": ["Architecture", "Historique"],
                    "coordonnees": [46.778904, 6.640619],
                    "open_season": "Toutes",
                    "url": "-",
                    "images": [
                        {
                            "source": "Roland Zumbühl (Picswiss), Arlesheim (Commons:Picswiss project), CC BY-SA 3.0, via Wikimedia Commons",
                            "url": "https://upload.wikimedia.org/wikipedia/commons/2/2f/Picswiss_VD-47-17.jpg"
                        },
                        {
                            "source": "Antoine Delage, CC BY-SA 4.0, via Wikimedia Commons",
                            "url": "https://upload.wikimedia.org/wikipedia/commons/2/20/Orgue_du_Temple_d%27Yverdon-les-Bains_Suisse.jpg"
                        }
                    ]
                },
                {
                    "nom": "Hôtel de Ville (1769)",
                    "description": "Construit entre 1767 et 1773 par l'architecte Abraham Burnand, cet édifice incarne l'autonomie des autorités communales face au souverain bernois. Situé sur la place Pestalozzi, il se distingue par sa façade en pierres jaunes de Neuchâtel, rythmée par des pilastres colossaux et divers types d'ouvertures. Destiné à accueillir les halles au rez-de-chaussée, l'administration au premier étagse et des locaux publics et logements au second, il a été conçu à partir d'un concours collaboratif entre les architectes Béat de Hennezel et Abraham Burnand.",
                    "tags": ["Architecture", "Historique"],
                    "coordonnees": [46.778527, 6.640818],
                    "open_season": "Été",
                    "url": "-",
                    "images": [
                        {
                            "source": "Olivier Anh, CC BY-SA 3.0, via Wikimedia Commons",
                            "url": "https://upload.wikimedia.org/wikipedia/commons/b/b2/H%C3%B4tel_de_Ville_d%27Yverdon_les_Bains.jpg"
                        }
                    ]
                },
                {
                    "nom": "Logis de l'Aigle Royal (XVIIIe siècle)",
                    "description": "Le bâtiment de l'Aigle royal, construit au XVIIIe siècle par Béat de Hennezel, fut une auberge puis l'institut pour jeunes filles de Johann Heinrich Pestalozzi en 1806. Inscrit comme bien culturel suisse d'importance nationale, il sert aujourd'hui d'annexe à l'hôtel de ville, surnommé Hôtel de Ville no 2.",
                    "tags": ["Architecture", "Historique"],
                    "coordonnees": [46.778488, 6.640374],
                    "open_season": "Toutes",
                    "url": "-",
                    "images": [
                        {
                            "source": "Olivier Anh, CC BY-SA 3.0, via Wikimedia Commons",
                            "url": "https://upload.wikimedia.org/wikipedia/commons/7/76/L%27ancien_h%C3%B4tel_de_l%27Aigle_%C3%A0_Yverdon_les_Bains.jpg"
                        }
                    ]
                },
                {
                    "nom": "Place Pestalozzi",
                    "description": "Influencé par Jean-Jacques Rousseau, Johann Heinrich Pestalozzi consacre sa vie à l'éducation des enfants pauvres, créant des écoles modèles en Europe. En 1806, il fonde plusieurs instituts à Yverdon, dont un pour jeunes filles et un pour sourds-muets.",
                    "tags": ["Historique"],
                    "coordonnees": [46.778659, 6.641027],
                    "open_season": "Toutes",
                    "url": "https://fr.wikipedia.org/wiki/Johann_Heinrich_Pestalozzi",
                    "images": [
                        {
                            "source": "-",
                            "url": "https://upload.wikimedia.org/wikipedia/commons/8/8a/Johann_Heinrich_Pestalozzi_%28Real_Academia_de_Bellas_Artes_de_San_Fernando%2C_Madrid%29.jpg"
                        },
                        {
                            "source": "Jean-Pierre Bösiger, CC BY-SA 4.0, via Wikimedia Commons",
                            "url": "https://upload.wikimedia.org/wikipedia/commons/3/35/Statue_Pestalozzi.jpg"
                        }
                    ]
                },
                {
                    "nom": "Centre historique",
                    "description": "Observez les rues piétonnes et découvrez les vestiges de l'ancien temps",
                    "tags": ["Historique"],
                    "coordonnees": [46.778659, 6.641027],
                    "open_season": "Toutes",
                    "url": "-",
                    "images": [
                        {
                            "source": "Roland Zumbühl (Picswiss), Arlesheim (Commons:Picswiss project), CC BY-SA 3.0, via Wikimedia Commons",
                            "url": "https://upload.wikimedia.org/wikipedia/commons/2/25/Picswiss_VD-47-14.jpg"
                        }
                    ]
                },
                {
                    "nom": "Château d'Yverdon (XIIIe siècle)",
                    "description": "Le château d'Yverdon, initialement habité par les seigneurs savoyards, est construit autour de 1235 par Amédée III de Montfaucon-Montbéliard. Vendu à Pierre II de Savoie en 1260, le château de plan quadrangulaire est érigé entre 1260 et 1265 pour protéger la ville. Devenu chef-lieu du bailliage d'Yverdon sous la domination bernoise en 1536, il sert de résidence aux baillis jusqu'en 1798. En 1805, la ville d'Yverdon achète le château, et Johann Heinrich Pestalozzi y installe son institut de 1805 à 1825. Le château est restauré au XXe siècle par les architectes Otto Schmid et Pierre Margot.",
                    "tags": ["Architecture", "Historique"],
                    "coordonnees": [46.777941, 6.641481],
                    "open_season": "Toutes",
                    "url": "http://chateau.yverdon.ch/accueil",
                    "images": [
                        {
                            "source": "Geri340, CC BY-SA 4.0, via Wikimedia Commons",
                            "url": "https://upload.wikimedia.org/wikipedia/commons/0/03/Das_Schloss_von_Yverdon-les-Bains_06.jpg"
                        }
                    ]
                }
            ]
        }
    ]
}
